py_bugger/__init__.py
py_bugger/buggers.py
py_bugger/py_bugger.py
py_bugger/cli/__init__.py
py_bugger/cli/cli.py
py_bugger/cli/cli_messages.py
py_bugger/cli/cli_utils.py
py_bugger/cli/config.py
py_bugger/utils/bug_utils.py
py_bugger/utils/cst_utils.py
py_bugger/utils/file_utils.py
py_bugger/utils/modification.py
python_bugger-0.5.2.dist-info/licenses/LICENSE
python_bugger-0.5.2.dist-info/METADATA
python_bugger-0.5.2.dist-info/WHEEL
python_bugger-0.5.2.dist-info/entry_points.txt
python_bugger-0.5.2.dist-info/top_level.txt
python_bugger-0.5.2.dist-info/RECORD
