Metadata-Version: 2.4
Name: python-bugger
Version: 0.5.2
Summary: Practice debugging, by intentionally introducing bugs into an existing codebase.
Project-URL: Documentation, https://py-bugger.readthedocs.io/en/latest/
Project-URL: GitHub, https://github.com/ehmatthes/py-bugger
Project-URL: Changelog, https://github.com/ehmatthes/py-bugger/blob/main/CHANGELOG.md
Requires-Python: >=3.9
License-File: LICENSE
Requires-Dist: libcst
Requires-Dist: click
Provides-Extra: dev
Requires-Dist: black>=24.1.0; extra == "dev"
Requires-Dist: build>=1.2.1; extra == "dev"
Requires-Dist: pytest>=8.3.0; extra == "dev"
Requires-Dist: pytest-xdist>=3.7.0; extra == "dev"
Requires-Dist: twine>=5.1.1; extra == "dev"
Requires-Dist: mkdocs>=1.6.0; extra == "dev"
Requires-Dist: mkdocs-material>=9.5.0; extra == "dev"
Dynamic: license-file
